fown/__init__.py
fown/cli/__init__.py
fown/cli/archive.py
fown/cli/auth.py
fown/cli/file.py
fown/cli/label.py
fown/cli/main.py
fown/cli/noti.py
fown/cli/product.py
fown/cli/script.py
fown/core/__init__.py
fown/core/models/__init__.py
fown/core/models/config.py
fown/core/services/__init__.py
fown/core/services/github.py
fown/core/utils/__init__.py
fown/core/utils/file_io.py
fown/data/default_config.yml
fown/data/label_templates.json
fown/tests/test_archive.py
fown-0.1.12.dist-info/entry_points.txt
fown-0.1.12.dist-info/LICENSE
fown-0.1.12.dist-info/METADATA
fown-0.1.12.dist-info/WHEEL
fown-0.1.12.dist-info/RECORD
