Metadata-Version: 2.1
Name: fown
Version: 0.1.12
Summary: Tiny Python CLI to automate GitHub labels and projects.
License: MIT
Author: bamjun
Author-email: khy5116@naver.com
Requires-Python: >=3.12,<4.0
Classifier: License :: OSI Approved :: MIT License
Classifier: Programming Language :: Python :: 3
Classifier: Programming Language :: Python :: 3.12
Requires-Dist: PyYAML (>=6.0,<7.0)
Requires-Dist: click (>=8.1.7,<9.0.0)
Requires-Dist: requests (>=2.31.0,<3.0.0)
Requires-Dist: rich (>=13.7.0,<14.0.0)
Requires-Dist: rich-click (>=1.7.2,<2.0.0)
Requires-Dist: textual (>=0.52.1,<0.53.0)
